odoo/addons/l10n_jp_address_layout/README.rst
odoo/addons/l10n_jp_address_layout/__init__.py
odoo/addons/l10n_jp_address_layout/__manifest__.py
odoo/addons/l10n_jp_address_layout/data/res_country_data.xml
odoo/addons/l10n_jp_address_layout/i18n/ja.po
odoo/addons/l10n_jp_address_layout/i18n/l10n_jp_address_layout.pot
odoo/addons/l10n_jp_address_layout/readme/CONTRIBUTORS.md
odoo/addons/l10n_jp_address_layout/readme/DESCRIPTION.md
odoo/addons/l10n_jp_address_layout/readme/USAGE.md
odoo/addons/l10n_jp_address_layout/static/description/icon.png
odoo/addons/l10n_jp_address_layout/static/description/index.html
odoo/addons/l10n_jp_address_layout/static/description/japan_address_layout.png
odoo/addons/l10n_jp_address_layout/views/res_partner_views.xml
odoo_addon_l10n_jp_address_layout-18.0.1.0.0.3.dist-info/METADATA
odoo_addon_l10n_jp_address_layout-18.0.1.0.0.3.dist-info/WHEEL
odoo_addon_l10n_jp_address_layout-18.0.1.0.0.3.dist-info/top_level.txt
odoo_addon_l10n_jp_address_layout-18.0.1.0.0.3.dist-info/RECORD
